{
  "generator-jhipster": {
    "applicationType": "monolith",
    "gitCompany": "",
    "baseName": "blog",
    "packageName": "br.com.blog",
    "packageFolder": "br/com/blog",
    "serverPort": 8080,
    "serviceDiscoveryType": false,
    "authenticationType": "jwt",
    "uaaBaseName": "../uaa",
    "cacheProvider": "ehcache",
    "enableHibernateCache": true,
    "websocket": false,
    "databaseType": "sql",
    "devDatabaseType": "h2Disk",
    "prodDatabaseType": "mysql",
    "searchEngine": false,
    "enableSwaggerCodegen": false,
    "messageBroker": false,
    "buildTool": "maven",
    "useSass": true,
    "clientPackageManager": "npm",
    "testFrameworks": ["protractor"],
    "enableTranslation": true,
    "nativeLanguage": "en",
    "languages": ["pt-pt", "en"],
    "clientFramework": "angularX",
    "jhiPrefix": "jhi",
    "jhipsterVersion": "6.10.1",
    "jwtSecretKey": "NzAyMjUxY2FmNzE2ZmZmYTM3YjQzYjkxMjY5YWEzNzEyOTNjMDU1ZDE0YjcyY2VmM2Q3MDZhY2YxMzM0YTQ2ZDEzYTliYTc1NTUwYmJhNmFlOWQzOGFkODk5ODc2YjMxN2ZmODZlOGJiNGM4OTUxZGViNGFhM2NkZDI3YWQ5MGQ=",
    "embeddableLaunchScript": false,
    "clientTheme": "none",
    "creationTimestamp": 1600139111560,
    "entitySuffix": "",
    "dtoSuffix": "DTO",
    "otherModules": [],
    "blueprints": [],
    "prettierJava": true
  },
  "git-provider": "GitHub",
  "git-company": "geovafc",
  "repository-name": "blog"
}
